task_6_syrkin/__init__.py
task_6_syrkin/report.py
task_6_syrkin/monaco_qualifying_report/__init__.py
task_6_syrkin/monaco_qualifying_report/file_parser.py
task_6_syrkin/monaco_qualifying_report/record.py
task_6_syrkin/monaco_qualifying_report/report_builder.py
task_6_syrkin-0.0.4.dist-info/entry_points.txt
task_6_syrkin-0.0.4.dist-info/LICENSE
task_6_syrkin-0.0.4.dist-info/WHEEL
task_6_syrkin-0.0.4.dist-info/METADATA
task_6_syrkin-0.0.4.dist-info/RECORD
