Metadata-Version: 2.1
Name: task_6_syrkin
Version: 0.0.4
Summary: Monaco 2018 Formula 1 Qualification Report
Author-email: Andrii Syrkin <avvaan1981@gmail.com>
Requires-Python: >=3.7
Classifier: License :: OSI Approved :: MIT License
Requires-Dist: pytest>=8.3.2
Requires-Dist: coverage>=7.6.1
Requires-Dist: parameterized>=0.9.0
Requires-Dist: setuptools>=75.1.0
Project-URL: Home, https://git.foxminded.ua/andrii-syrkin-py_ment/task_6.git
